paws/lambda-time-trigger/__init__.py
paws/lambda-time-trigger/py.typed
paws/lambda-time-trigger/_jsii/__init__.py
paws/lambda-time-trigger/_jsii/paws-lambda-time-trigger@1.0.0.jsii.tgz
paws.lambda_time_trigger-1.0.0.dist-info/LICENSE
paws.lambda_time_trigger-1.0.0.dist-info/METADATA
paws.lambda_time_trigger-1.0.0.dist-info/WHEEL
paws.lambda_time_trigger-1.0.0.dist-info/top_level.txt
paws.lambda_time_trigger-1.0.0.dist-info/RECORD
