Metadata-Version: 2.1
Name: paws.lambda-time-trigger
Version: 1.0.0
Summary: Implements sub-minute time trigger support to trigger AWS Lambda functions
Home-page: https://github.com/ChristianEder/paws/packages/lambda-time-trigger
Author: Christian Eder<christian.johann.eder@googlemail.com>
License: Apache-2.0
Project-URL: Source, https://github.com/ChristianEder/paws.git
Platform: UNKNOWN
Classifier: Intended Audience :: Developers
Classifier: Operating System :: OS Independent
Classifier: Programming Language :: JavaScript
Classifier: Programming Language :: Python :: 3 :: Only
Classifier: Programming Language :: Python :: 3.6
Classifier: Programming Language :: Python :: 3.7
Classifier: Programming Language :: Python :: 3.8
Classifier: Programming Language :: Python :: 3.9
Classifier: Typing :: Typed
Classifier: License :: OSI Approved
Requires-Python: >=3.6
License-File: LICENSE
Requires-Dist: aws-cdk-lib (==2.8.0)
Requires-Dist: constructs (<11.0.0,>=10.0.0)
Requires-Dist: jsii (<2.0.0,>=1.52.1)
Requires-Dist: publication (>=0.0.3)
